Workbook

Sheet README
A1: Addendum A — LIVE model (rebuilt 17/09/2026)
A3: Why this exists: the source Addendum_A_Model.xlsx (16/09/2026) contains ZERO formulas in 632 cells.
A4: Every figure in it is a typed constant, so no assumption can be tested. This rebuild reproduces its
A5: structure and its numbers, but drives them from one Assumptions sheet.
A7: HOW TO USE
A8: Yellow cells on Assumptions are inputs. Change one and every sheet recalculates.
A9: Blue cells are calculated — do not type over them.
A11: SHEETS
A12: Assumptions every input, in one place
A13: Income_Bridge_Revised the Irish tax correction — THE key sheet. Verify with an Irish tax adviser.
A14: PL_AssetLight 5-year P&L for the kitting-first business
A15: Exit_Value build-for-exit at 10% Irish CGT (Revised Entrepreneur Relief)
... A40: Model numbers are (O) planning assumptions unless a source is cited.

Sheet Assumptions
A1: Assumptions — yellow cells are inputs
A2: Change an input and every other sheet recalculates.
A4: Parameter | B4: Value | C4: Unit | D4: Source / note
A5: PERSONAL TAX (Ireland)
A6: Irish income tax — higher rate | B6: 0.4 | C6: % | D6: (F) 2026 higher rate
A7: USC — top band | B7: 0.08 | C7: % | D7: (F)
A8: PRSI | B8: 0.042 | C8: % | D8: (F) 4.2%; rises to 4.35% from 10/2026 — change this cell then
A9: Slovak dividend withholding (credited) | B9: 0.07 | C9: % | D9: (F) treaty credit against Irish liability
A10: TARGET & OWNERSHIP
A11: Target net income | B11: 7500 | C11: EUR | D11: (F) your stated goal, per month
A12: Your ownership | B12: 1 | C12: % | D12: (O) 100% asset-light; original plan assumed 70%
A13: Dividend payout ratio | B13: 0.9 | C13: % | D13: (O) 10% retained
A14: COMPANY TAX (Slovakia)
A15: Corporate tax — low rate | B15: 0.1 | C15: % | D15: (R) SK CIT 10% for revenue <= threshold — confirm with accountant
A16: Low-rate revenue threshold | B16: 100000 | C16: EUR | D16: (R)
A17: Corporate tax — standard rate | B17: 0.21 | C17: % | D17: (R) 21%; 24% only above EUR5m revenue
A18: OPERATIONS
A19: Pack price | B19: 28 | C19: EUR | D19: (R) LOAD-BEARING and UNVERIFIED. Output of the 'Cost the Pack' sprint
A20: Capex — container kitting line | B20: 120000 | C20: EUR | D20: (F, Addendum A) 2028
A21: Capex — racking + WMS | B21: 40000 | C21: EUR | D21: (F, Addendum A) 2029
A22: Depreciation period | B22: 8 | D22: (O) straight line, years
A23: Grant released to income (per yr) | B23: 10000 | C23: EUR | D23: (O) from 2028
A24: EXIT
A25: EBITDA multiple at exit | B25: 5 | D25: (O) small-company trade sale
A26: Irish CGT — Entrepreneur Relief rate | B26: 0.1 | C26: % | D26: (F) Revised ER, from 01/01/2026
A27: Entrepreneur Relief lifetime limit | B27: 1500000 | C27: EUR | D27: (F) raised from EUR1m in Budget 2026
A28: Irish CGT — standard rate above limit | B28: 0.33 | C28: % | D28: (F)
A30: Irish marginal rate (computed) | B30: =Assumptions!$B$6+Assumptions!$B$7+Assumptions!$B$8 | D30: (F) sum of the three bands; Slovak 7% is credited, not added

Sheet Income_Bridge_Revised
A1: Income bridge — the Irish tax correction
A2: THE key sheet of Addendum A. Verify with an Irish chartered tax adviser before acting.
A4: Step | B4: Model as written (7% SK) | C4: Reality: Irish-resident | D4: Irish-resident, your ownership | E4: Note
A5: Target net income per year | B5: =Assumptions!$B$11*12 | C5: =Assumptions!$B$11*12 | D5: =Assumptions!$B$11*12 | E5: your goal x 12
A6: Gross dividend needed | B6: =B5/(1-Assumptions!$B$9) | C6: =C5/(1-Assumptions!$B$30) | D6: =D5/(1-Assumptions!$B$30) | E6: personal tax on the dividend
A7: / your ownership | B7: =B6/0.7 | C7: =C6/0.7 | D7: =D6/Assumptions!$B$12 | E7: 70% in the original plan; the 4th column uses your Assumptions input
A8: / payout ratio | B8: =B7/Assumptions!$B$13 | C8: =C7/Assumptions!$B$13 | D8: =D7/Assumptions!$B$13 | E8: 10% retained
A9: PROFIT BEFORE TAX NEEDED | B9: =B8/(1-Assumptions!$B$17) | C9: =C8/(1-Assumptions!$B$17) | D9: =D8/(1-Assumptions!$B$17) | E9: at the Slovak standard corporate rate
A10: Revenue needed at 8% pre-tax margin | B10: =B9/0.08 | C10: =C9/0.08 | D10: =D9/0.08 | E10: (R)
A11: Revenue needed at 12% pre-tax margin | B11: =B9/0.12 | C11: =C9/0.12 | D11: =D9/0.12 | E11: (R)
A12: Revenue needed at 20% pre-tax margin | B12: =B9/0.2 | C12: =C9/0.2 | D12: =D9/0.2 | E12: (R)
A14: Irish marginal rate build-up
A15: Income tax | B15: =Assumptions!$B$6
A16: USC | B16: =Assumptions!$B$7
A17: PRSI | B17: =Assumptions!$B$8
A18: Total marginal rate | B18: =Assumptions!$B$30 | E18: credit given for the 7% Slovak withholding (F, treaty)

Sheet PL_AssetLight
A1: P&L — asset-light (kitting-first) business
A2: Revenue lines are inputs (yellow). Everything below Gross profit is calculated.
A4: Line | B4: 2027 | C4: 2028 | D4: 2029 | E4: 2030 | F4: 2031
A5: Revenue — brokerage (Tier 0) | B5: 150000 | C5: 200000 | D5: 150000 | E5: 120000 | F5: 100000
A6: Revenue — kitting (Tier 1) | B6: 0 | C6: 380000 | D6: 950000 | E6: 1600000 | F6: 2100000
A7: Revenue — reserve service (Tier 2) | B7: 0 | C7: 40000 | D7: 120000 | E7: 260000 | F7: 420000
A8: Revenue — software (LEANTA) | B8: 12000 | C8: 48000 | D8: 96000 | E8: 144000 | F8: 180000
A9: TOTAL REVENUE | B9: =SUM(B5:B8) | C9: =SUM(C5:C8) | D9: =SUM(D5:D8) | E9: =SUM(E5:E8) | F9: =SUM(F5:F8)
A10: Gross margin % | B10: 0.13 | C10: 0.21 | D10: 0.25 | E10: 0.27 | F10: 0.28
A11: Gross profit | B11: =B9*B10 | C11: =C9*C10 | D11: =D9*D10 | E11: =E9*E10 | F11: =F9*F10
A12: Fixed overheads | B12: 28000 | C12: 110000 | D12: 190000 | E12: 280000 | F12: 350000
A13: EBITDA | B13: =B11-B12 | C13: =C11-C12 | D13: =D11-D12 | E13: =E11-E12 | F13: =F11-F12
A14: Depreciation | B14: 0 | C14: =Assumptions!$B$20/Assumptions!$B$22 | D14: =(Assumptions!$B$20+Assumptions!$B$21)/Assumptions!$B$22 | E14: =(Assumptions!$B$20+Assumptions!$B$21)/Assumptions!$B$22 | F14: =(Assumptions!$B$20+Assumptions!$B$21)/Assumptions!$B$22
A15: Grant released to income | B15: 0 | C15: =Assumptions!$B$23 | D15: =Assumptions!$B$23 | E15: =Assumptions!$B$23 | F15: =Assumptions!$B$23
A16: Interest | B16: 0 | C16: 6000 | D16: 6000 | E16: 5000 | F16: 4000
A17: PROFIT BEFORE TAX | B17: =B13-B14+B15-B16 | C17: =C13-C14+C15-C16 | D17: =D13-D14+D15-D16 | E17: =E13-E14+E15-E16 | F17: =F13-F14+F15-F16
A18: Corporate tax | B18: =IF(B17<=0,0,B17*IF(B9<=Assumptions!$B$16,Assumptions!$B$15,Assumptions!$B$17)) | C18: =IF(C17<=0,0,C17*IF(C9<=Assumptions!$B$16,Assumptions!$B$15,Assumptions!$B$17)) | D18: =IF(D17<=0,0,D17*IF(D9<=Assumptions!$B$16,Assumptions!$B$15,Assumptions!$B$17)) | E18: =IF(E17<=0,0,E17*IF(E9<=Assumptions!$B$16,Assumptions!$B$15,Assumptions!$B$17)) | F18: =IF(F17<=0,0,F17*IF(F9<=Assumptions!$B$16,Assumptions!$B$15,Assumptions!$B$17))
A19: Net profit | B19: =B17-B18 | C19: =C17-C18 | D19: =D17-D18 | E19: =E17-E18 | F19: =F17-F18
A20: Your net income / month (Irish-resident) | B20: =MAX(0,B19)*Assumptions!$B$13*Assumptions!$B$12*(1-Assumptions!$B$30)/12 | C20: =MAX(0,C19)*Assumptions!$B$13*Assumptions!$B$12*(1-Assumptions!$B$30)/12 | D20: =MAX(0,D19)*Assumptions!$B$13*Assumptions!$B$12*(1-Assumptions!$B$30)/12 | E20: =MAX(0,E19)*Assumptions!$B$13*Assumptions!$B$12*(1-Assumptions!$B$30)/12 | F20: =MAX(0,F19)*Assumptions!$B$13*Assumptions!$B$12*(1-Assumptions!$B$30)/12
A21: Gap to target | B21: =B20-Assumptions!$B$11 | C21: =C20-Assumptions!$B$11 | D21: =D20-Assumptions!$B$11 | E21: =E20-Assumptions!$B$11 | F21: =F20-Assumptions!$B$11
A22: Target met? | B22: =IF(B20>=Assumptions!$B$11,"Yes","No") | C22: =IF(C20>=Assumptions!$B$11,"Yes","No") | D22: =IF(D20>=Assumptions!$B$11,"Yes","No") | E22: =IF(E20>=Assumptions!$B$11,"Yes","No") | F22: =IF(F20>=Assumptions!$B$11,"Yes","No")
A24: GATE 0 — 30/06/2027 | B24: >=EUR50k Tier 0 revenue + 1 state reference; else STOP (<EUR8k spent)
A25: GATE 1 — 31/12/2027 | B25: >=2 co-packing agreements + >=EUR300k contracted demand + grant decision; else stay a broker
A26: GATE 2 — 31/12/2029 | B26: EBITDA >= EUR100k + reserve contract signed; else sell the book, keep the software

Sheet Exit_Value
A1: Exit value at 10% Irish CGT (Revised Entrepreneur Relief)
A2: (O) Compare: the same money taken as dividends while Irish-resident is taxed at the marginal rate.
A4: EBITDA at exit | B4: Multiple | C4: Enterprise value | D4: Ownership | E4: Your share | F4: CGT | G4: Net to you | H4: Years of target
A5: 150000 | B5: =Assumptions!$B$25 | C5: =A5*B5 | D5: 0.7 | E5: =C5*D5 | F5: =MIN(E5,Assumptions!$B$27)*Assumptions!$B$26+MAX(0,E5-Assumptions!$B$27)*Assumptions!$B$28 | G5: =E5-F5 | H5: =G5/(Assumptions!$B$11*12)
A6: 150000 | B6: =Assumptions!$B$25 | C6: =A6*B6 | D6: 1 | E6: =C6*D6 | F6: =MIN(E6,Assumptions!$B$27)*Assumptions!$B$26+MAX(0,E6-Assumptions!$B$27)*Assumptions!$B$28 | G6: =E6-F6 | H6: =G6/(Assumptions!$B$11*12)
A7: 250000 | B7: =Assumptions!$B$25 | C7: =A7*B7 | D7: 0.7 | E7: =C7*D7 | F7: =MIN(E7,Assumptions!$B$27)*Assumptions!$B$26+MAX(0,E7-Assumptions!$B$27)*Assumptions!$B$28 | G7: =E7-F7 | H7: =G7/(Assumptions!$B$11*12)
A8: 250000 | B8: =Assumptions!$B$25 | C8: =A8*B8 | D8: 1 | E8: =C8*D8 | F8: =MIN(E8,Assumptions!$B$27)*Assumptions!$B$26+MAX(0,E8-Assumptions!$B$27)*Assumptions!$B$28 | G8: =E8-F8 | H8: =G8/(Assumptions!$B$11*12)
A9: 400000 | B9: =Assumptions!$B$25 | C9: =A9*B9 | D9: 0.7 | E9: =C9*D9 | F9: =MIN(E9,Assumptions!$B$27)*Assumptions!$B$26+MAX(0,E9-Assumptions!$B$27)*Assumptions!$B$28 | G9: =E9-F9 | H9: =G9/(Assumptions!$B$11*12)
A10: 400000 | B10: =Assumptions!$B$25 | C10: =A10*B10 | D10: 1 | E10: =C10*D10 | F10: =MIN(E10,Assumptions!$B$27)*Assumptions!$B$26+MAX(0,E10-Assumptions!$B$27)*Assumptions!$B$28 | G10: =E10-F10 | H10: =G10/(Assumptions!$B$11*12)
A11: =PL_AssetLight!F13 | B11: =Assumptions!$B$25 | C11: =A11*B11 | D11: 0.7 | E11: =C11*D11 | F11: =MIN(E11,Assumptions!$B$27)*Assumptions!$B$26+MAX(0,E11-Assumptions!$B$27)*Assumptions!$B$28 | G11: =E11-F11 | H11: =G11/(Assumptions!$B$11*12)
A12: =PL_AssetLight!F13 | B12: =Assumptions!$B$25 | C12: =A12*B12 | D12: 1 | E12: =C12*D12 | F12: =MIN(E12,Assumptions!$B$27)*Assumptions!$B$26+MAX(0,E12-Assumptions!$B$27)*Assumptions!$B$28 | G12: =E12-F12 | H12: =G12/(Assumptions!$B$11*12)
A14: (F) Revised Entrepreneur Relief: 10% CGT, lifetime limit EUR1.5m from 01/01/2026; >=5% ordinary shares; director/employee >=50% of working time for 3 of the previous 5 years.

Sheet Funding_Portfolio
A1: Funding portfolio — probability that at least one application succeeds
A2: (R) Probabilities are judgement, not published statistics. Edit them; the maths follows.
A4: # | B4: Instrument | C4: Type / size | D4: Use | E4: Success (R) | F4: Include? | G4: (1-p) if included
A5: 1 | B5: LEO Feasibility grant (IE) | C5: grant, ~EUR15k, 50% | D5: Market study | E5: 0.6 | F5: 1 | G5: =IF(F5=1,1-E5,1)
A6: 2 | B6: LEO Priming grant (IE) | C6: 50% or EUR150,000 max (F) | D6: Irish entity first-year costs | E6: 0.45 | F6: 1 | G6: =IF(F6=1,1-E6,1)
A7: 3 | B7: Enterprise Ireland / IDA defence | C7: grants/equity/loans (F, 2026 Bill) | D7: Export & capability | E7: 0.3 | F7: 1 | G7: =IF(F7=1,1-E7,1)
A8: 4 | B8: Regionalny prispevok (MIRRI, RS) | C8: LAPSED 05/10/2026; next call expected 2027 (F) | D8: Kitting line, jobs | E8: 0.45 | F8: 0 | G8: =IF(F8=1,1-E8,1)
A9: 5 | B9: Just Transition Fund (BB region) | C9: MSME grants to EUR800,000 (F) | D9: Productive investment | E9: 0.4 | F9: 1 | G9: =IF(F9=1,1-E9,1)
A10: 6 | B10: PPA intervention 73.7 | C10: EUR35m call (F) | D10: Tier 3 line | E10: 0.35 | F10: 1 | G10: =IF(F10=1,1-E10,1)
A11: 7 | B11: LEADER / CLLD via MAS | C11: EUR10-100k (R) | D11: Small equipment | E11: 0.5 | F11: 1 | G11: =IF(F11=1,1-E11,1)
A12: 8 | B12: Interreg SK-HU small project fund | C12: small cross-border (R) | D12: Preparedness pilot | E12: 0.4 | F12: 1 | G12: =IF(F12=1,1-E12,1)
A13: 9 | B13: Visegrad Fund | C13: EUR25-35k; small grants <=EUR6k (F) | D13: Education project only | E13: 0.4 | F13: 1 | G13: =IF(F13=1,1-E13,1)
A14: 10 | B14: SBA / NHF microloan | C14: EUR2,500-50,000; 1.19-9.03% (F) | D14: Equipment / working capital | E14: 0.68 | F14: 1 | G14: =IF(F14=1,1-E14,1)
A15: 11 | B15: SZRB INVESTaktiv (EIF guarantee) | C15: investment to 20 yrs (F) | D15: Tier 3 plant | E15: 0.6 | F15: 1 | G15: =IF(F15=1,1-E15,1)
A16: 12 | B16: SIH / MH SR NDF III | C16: to EUR2.8m, 80% guarantee (F) | D16: Tier 3 plant | E16: 0.6 | F16: 1 | G16: =IF(F16=1,1-E16,1)
... A18: 14 | B18: EDIP | C18: EUR1.5bn WP 2026-27 (F) | D18: Later, consortium only | E18: 0.1 | F18: 1 | G18: =IF(F18=1,1-E18,1)
B20: P(at least one succeeds), included rows | E20: =1-PRODUCT($G$5:$G$18)
B21: Set Include? to 0/1 to test a smaller portfolio
B22: Rule (O): submit >=3 INDEPENDENT applications, different systems, different calendars.
B23: Regionalny prispevok is set to Include?=0: the 05/10/2026 call lapsed. Next call expected 2027.
B24: TRAP (F): SZRB lends UNDER the SIH NDF III guarantee - they are ONE mechanism, not two legs.
B25: Independent trio clearing 90%: microloan 68% + LEO Feasibility 60% + LEADER 50% = 93.6%.
B26: Three applications to the same ministry are one application wearing three hats.

Sheet Sector_Scoring_v2
A1: Sector scoring v2 — with a Reversibility criterion
A2: The dossier's sheet had no measure of capital at risk before revenue. That omission is why it ranks the EUR600k bakery #1 while Addendum A rejects it.
A4: Option | B4: Fit with skills | C4: Demand security | D4: Low capital need | E4: Grant eligibility | F4: Margin | G4: Speed to cash | H4: Reversibility | I4: Weighted score | J4: Rank
A5: Weight (edit) | B5: 0.2 | C5: 0.16 | D5: 0.12 | E5: 0.12 | F5: 0.12 | G5: 0.08 | H5: 0.2 | I5: =SUM(B5:H5) | J5: =IF(ABS(I5-1)<0.0001,"OK","WEIGHTS != 100%")
A6: Tier 0 — broker / agent | B6: 4 | C6: 4 | D6: 5 | E6: 2 | F6: 2 | G6: 5 | H6: 5 | I6: =SUMPRODUCT($B$5:$H$5,B6:H6) | J6: =RANK(I6,$I$6:$I$11)
A7: Tier 1 — kitter / assembler | B7: 4 | C7: 4 | D7: 4 | E7: 4 | F7: 3 | G7: 3 | H7: 4 | I7: =SUMPRODUCT($B$5:$H$5,B7:H7) | J7: =RANK(I7,$I$6:$I$11)
A8: Tier 2 — reserve service | B8: 4 | C8: 5 | D8: 4 | E8: 3 | F8: 4 | G8: 2 | H8: 3 | I8: =SUMPRODUCT($B$5:$H$5,B8:H8) | J8: =RANK(I8,$I$6:$I$11)
A9: Shelf-stable bakery (dossier rec.) | B9: 5 | C9: 4 | D9: 2 | E9: 5 | F9: 3 | G9: 3 | H9: 1 | I9: =SUMPRODUCT($B$5:$H$5,B9:H9) | J9: =RANK(I9,$I$6:$I$11)
A10: Lubricants: distribution -> blending | B10: 2 | C10: 4 | D10: 4 | E10: 3 | F10: 4 | G10: 4 | H10: 3 | I10: =SUMPRODUCT($B$5:$H$5,B10:H10) | J10: =RANK(I10,$I$6:$I$11)
A11: Wooden packaging / pallets / crates | B11: 3 | C11: 4 | D11: 3 | E11: 4 | F11: 2 | G11: 3 | H11: 2 | I11: =SUMPRODUCT($B$5:$H$5,B11:H11) | J11: =RANK(I11,$I$6:$I$11)
A13: (F) Original dossier weights: Fit 25% · Demand 20% · Low capital 15% · Grant 15% · Margin 15% · Speed 10%.
A14: (O) Reversibility added at 20%, the other six scaled by 0.8 so the weights still sum to 100%.
A15: (O) Reversibility = how much committed capital survives if the venture fails. A container line resells;
A16: a hall fit-out and a certification do not.
A17: (R) Scores are judgement. Replace them with yours — that is the point of this sheet.

Sheet Tier_Ladder
A1: Tier ladder — positioning from cheapest to most expensive
A2: Descriptive reference (F, Addendum A).
A4: Tier | B4: What you sell | C4: Capex (EUR) | D4: Gross margin | E4: Time to first cash | F4: Win probability (R) | G4: Verdict
A5: 0 — Broker/agent | B5: Resell certified rations & kits into SK tenders, back-to-back | C5: 2,000-5,000 | D5: 6-12% | E5: 60-90 days | F5: High | G5: Start here Q4 2026
A6: 1 — Kitter/assembler | B6: Assemble ration packs & 72h civil kits under own HACCP | C6: 120,000-180,000 | D6: 18-26% | E6: 9-14 months | F6: Medium-high | G6: Core business 2027-28
A7: 2 — Reserve service | B7: Hold & rotate state/municipal stock for an annual fee | C7: 40,000-90,000 | D7: 25-40% on fee | E7: 12-24 months | F7: Medium | G7: The annuity — highest value
A8: 3 — Own production | B8: Shelf-stable bakery / retort / lyo line (original plan) | C8: 450,000-700,000 | D8: 30-38% | E8: 24-36 months | F8: Medium | G8: Only after Tier 1 contracts
A9: 4 — Deployable modules | B9: Containerised field bakery/kitchen/packing, sold or leased | C9: 150,000-400,000/unit | D9: 25-35% | E9: 18-30 months | F9: Low-medium | G9: Export & NSPA upside
